cycls/__init__.py
cycls/cycls.py
cycls/key.pub
cycls_dev-0.0.1.3.dist-info/METADATA
cycls_dev-0.0.1.3.dist-info/WHEEL
cycls_dev-0.0.1.3.dist-info/RECORD
