Metadata-Version: 2.1
Name: cycls-dev
Version: 0.0.1.3
Summary: Cycls SDK
Author: Mohammed Jamal
Author-email: mj@cycls.com
Requires-Python: >=3.8,<4.0
Classifier: Programming Language :: Python :: 3
Classifier: Programming Language :: Python :: 3.8
Classifier: Programming Language :: Python :: 3.9
Classifier: Programming Language :: Python :: 3.10
Classifier: Programming Language :: Python :: 3.11
Classifier: Programming Language :: Python :: 3.12
Requires-Dist: fastapi (>=0.111.0,<0.112.0)
Requires-Dist: httpx (>=0.27.0,<0.28.0)
